adafruit_shell.py
adafruit_python_shell-1.9.0.dist-info/LICENSE
adafruit_python_shell-1.9.0.dist-info/METADATA
adafruit_python_shell-1.9.0.dist-info/WHEEL
adafruit_python_shell-1.9.0.dist-info/top_level.txt
adafruit_python_shell-1.9.0.dist-info/RECORD
