Metadata-Version: 2.2
Name: adafruit-python-shell
Version: 1.9.0
Summary: Python helper for running Shell scripts in Python
Author-email: Adafruit Industries <circuitpython@adafruit.com>
License: MIT
Project-URL: Homepage, https://github.com/adafruit/Adafruit_Python_Shell
Keywords: adafruit,blinka,circuitpython,micropython,python,shell,installation,raspberry,pi,console,terminal,installer
Classifier: Development Status :: 3 - Alpha
Classifier: Intended Audience :: Developers
Classifier: Topic :: Software Development :: Libraries
Classifier: Topic :: System :: Hardware
Classifier: License :: OSI Approved :: MIT License
Classifier: Programming Language :: Python :: 3
Classifier: Programming Language :: Python :: 3.4
Classifier: Programming Language :: Python :: 3.5
License-File: LICENSE
Requires-Dist: clint
Requires-Dist: Adafruit-PlatformDetect
Provides-Extra: optional
